oc/__init__.py
oc/api.py
oc/utils.py
oc-0.2.1.dist-info/LICENSE
oc-0.2.1.dist-info/METADATA
oc-0.2.1.dist-info/WHEEL
oc-0.2.1.dist-info/top_level.txt
oc-0.2.1.dist-info/RECORD
