Metadata-Version: 2.1
Name: oc
Version: 0.2.1
Summary: OpenShift CLI (oc) thin wrapper library for Python3
Home-page: https://github.com/peaqe/oc/
Author: Rudá Moura
Author-email: rmoura@redhat.com
License: Apache License
Platform: UNKNOWN
Classifier: Programming Language :: Python :: 3
Classifier: License :: OSI Approved :: Apache Software License
Classifier: Topic :: Software Development :: Libraries
Requires-Dist: pexpect
